{
  "name": "heksa",
  "full_name": "heksa",
  "tap": "homebrew/core",
  "oldname": null,
  "oldnames": [],
  "aliases": [],
  "versioned_formulae": [],
  "desc": "CLI hex dumper with colors",
  "license": "Apache-2.0",
  "homepage": "https://github.com/raspi/heksa",
  "versions": {
    "stable": "1.14.0",
    "head": "HEAD",
    "bottle": true
  },
  "urls": {
    "stable": {
      "url": "https://github.com/raspi/heksa.git",
      "tag": "v1.14.0",
      "revision": "045ea335825556c856b2f4dee606ae91c61afe7d",
      "checksum": null
    },
    "head": {
      "url": "https://github.com/raspi/heksa.git",
      "branch": "master"
    }
  },
  "revision": 0,
  "version_scheme": 0,
  "bottle": {
    "stable": {
      "rebuild": 0,
      "root_url": "https://ghcr.io/v2/homebrew/core",
      "files": {
        "arm64_ventura": {
          "cellar": ":any_skip_relocation",
          "url": "https://ghcr.io/v2/homebrew/core/heksa/blobs/sha256:89b15d07d2e29580a0ee9b2f71fc60f36b71e2e7bfb8c460e24fcc5f005bd9e8",
          "sha256": "89b15d07d2e29580a0ee9b2f71fc60f36b71e2e7bfb8c460e24fcc5f005bd9e8"
        },
        "arm64_monterey": {
          "cellar": ":any_skip_relocation",
          "url": "https://ghcr.io/v2/homebrew/core/heksa/blobs/sha256:f4cab211255c75ce7044df346f1b85d3a548c2a760be570a10fcc970a3aec5fb",
          "sha256": "f4cab211255c75ce7044df346f1b85d3a548c2a760be570a10fcc970a3aec5fb"
        },
        "arm64_big_sur": {
          "cellar": ":any_skip_relocation",
          "url": "https://ghcr.io/v2/homebrew/core/heksa/blobs/sha256:de0c36cdc7215c90ea71792580f298717eeffc2b8d6e7a556cd55e4a9c6fd43e",
          "sha256": "de0c36cdc7215c90ea71792580f298717eeffc2b8d6e7a556cd55e4a9c6fd43e"
        },
        "ventura": {
          "cellar": ":any_skip_relocation",
          "url": "https://ghcr.io/v2/homebrew/core/heksa/blobs/sha256:3bff648f15075466f5e8ddfa77e7092428b6d294091c8f95dabf53e6688a97f6",
          "sha256": "3bff648f15075466f5e8ddfa77e7092428b6d294091c8f95dabf53e6688a97f6"
        },
        "monterey": {
          "cellar": ":any_skip_relocation",
          "url": "https://ghcr.io/v2/homebrew/core/heksa/blobs/sha256:2c40667b5945ee8ce31d17eef4edb72b05d2238bf6a19210885d29471218eb1a",
          "sha256": "2c40667b5945ee8ce31d17eef4edb72b05d2238bf6a19210885d29471218eb1a"
        },
        "big_sur": {
          "cellar": ":any_skip_relocation",
          "url": "https://ghcr.io/v2/homebrew/core/heksa/blobs/sha256:f58fd184f70cb5601d2da5737aff2add348d98eeb7724460dbdbebef04bd9ea6",
          "sha256": "f58fd184f70cb5601d2da5737aff2add348d98eeb7724460dbdbebef04bd9ea6"
        },
        "catalina": {
          "cellar": ":any_skip_relocation",
          "url": "https://ghcr.io/v2/homebrew/core/heksa/blobs/sha256:98f162aca970fdb91350424f8f4fcf94348b07d598a32355c6e2dfda57b31150",
          "sha256": "98f162aca970fdb91350424f8f4fcf94348b07d598a32355c6e2dfda57b31150"
        },
        "mojave": {
          "cellar": ":any_skip_relocation",
          "url": "https://ghcr.io/v2/homebrew/core/heksa/blobs/sha256:deb7aa04db9d74d1300c7b5bfc85243cc853eb7bf81ca0657b3c7bfa6bf499a9",
          "sha256": "deb7aa04db9d74d1300c7b5bfc85243cc853eb7bf81ca0657b3c7bfa6bf499a9"
        },
        "x86_64_linux": {
          "cellar": ":any_skip_relocation",
          "url": "https://ghcr.io/v2/homebrew/core/heksa/blobs/sha256:a0c2fa3a47b5d6a492a5bd6b3c881b19714c459adaf3103d1313e9cf9213386a",
          "sha256": "a0c2fa3a47b5d6a492a5bd6b3c881b19714c459adaf3103d1313e9cf9213386a"
        }
      }
    }
  },
  "keg_only": false,
  "keg_only_reason": null,
  "options": [],
  "build_dependencies": [
    "go"
  ],
  "dependencies": [],
  "test_dependencies": [],
  "recommended_dependencies": [],
  "optional_dependencies": [],
  "uses_from_macos": [],
  "uses_from_macos_bounds": [],
  "requirements": [],
  "conflicts_with": [],
  "conflicts_with_reasons": [],
  "link_overwrite": [],
  "caveats": null,
  "installed": [],
  "linked_keg": null,
  "pinned": false,
  "outdated": false,
  "deprecated": false,
  "deprecation_date": null,
  "deprecation_reason": null,
  "disabled": false,
  "disable_date": null,
  "disable_reason": null,
  "post_install_defined": false,
  "service": null,
  "tap_git_head": "4eeae4ea50839e967536ba646d5e0ed6fbcbad7f",
  "ruby_source_path": "Formula/heksa.rb",
  "ruby_source_checksum": {
    "sha256": "0923639615bb72db4e9294d7c4cc4c62c753ecb91448b4f451f04073fa394f5d"
  },
  "date_added": "2020-06-23T17:12:31+00:00",
  "readme": "# heksa\n\n![Screenshot](https://github.com/raspi/heksa/blob/master/_assets/screenshot.png)\n\n![GitHub All Releases](https://img.shields.io/github/downloads/raspi/heksa/total?style=for-the-badge)\n![GitHub release (latest by date)](https://img.shields.io/github/v/release/raspi/heksa?style=for-the-badge)\n![GitHub tag (latest by date)](https://img.shields.io/github/v/tag/raspi/heksa?style=for-the-badge)\n[![Go Report Card](https://goreportcard.com/badge/github.com/raspi/heksa)](https://goreportcard.com/report/github.com/raspi/heksa)\n\n[![Packaging status](https://repology.org/badge/vertical-allrepos/heksa.svg)](https://repology.org/project/heksa/versions)\n\nHex dumper with colors\n\n## Features\n\n* [ANSI colors](https://en.wikipedia.org/wiki/ANSI_escape_code#Colors) for different byte groups such as \n  * Printable: A-Z, a-z, 0-9\n  * Spaces: space, tab, new line\n  * Special: 0x00, 0xFF\n* Output multiple formats at once ([hexadecimal](https://en.wikipedia.org/wiki/Hexadecimal), [decimal](https://en.wikipedia.org/wiki/Decimal), [octal](https://en.wikipedia.org/wiki/Octal), [bits](https://en.wikipedia.org/wiki/Binary_number) or special combination formats)\n* Multiple offset formats (hexadecimal, decimal, octal, percentage)\n  * First one is displayed on left side and second one on the right side\n* Read only N bytes\n* Seek to given offset\n  * also reads from end of file when using minus sign\n* Seek and limit supports \n  * Prefixes hex (`0x`), octal (`0o`) and binary (`0b`)\n  * Units (KB, KiB, MB, MiB, GB, GiB, TB, TiB)\n* Print relative offset starting from zero if seeking a file\n* Read from [stdin](https://en.wikipedia.org/wiki/Standard_streams#Standard_input_(stdin))\n\n![Screenshot](https://github.com/raspi/heksa/blob/master/_assets/screenshot2.png)\n\n## heksa --help\n\n```\nheksa - hex file dumper v1.14.0 - (2021-05-18T16:20:59+03:00)\n(c) Pekka Järvinen 2019- [ https://github.com/raspi/heksa ]\nSYNOPSIS:\n    heksa [--format|-f <fmt1,fmt2,..>] [--help|-h|-?]\n          [--limit|-l <[prefix]bytes[unit]>] [--offset-format|-o <fmt1[,fmt2]>]\n          [--print-relative-offset|-r] [--seek|-s <[prefix]offset[unit]>]\n          [--splitter|-S <size>] [--version] [--width|-w <[prefix]width>]\n          <filename> or STDIN\n\nOPTIONS:\n    --format|-f <fmt1,fmt2,..>          One or multiple of: asc, bit, bitwasc, bitwdec, bitwhex, blk, dec, decwasc, hex, hexwasc, oct (default: \"hex,asc\")\n\n    --help|-h|-?                        Show this help (default: false)\n\n    --limit|-l <[prefix]bytes[unit]>    Read only N bytes (0 = no limit). See NOTES. (default: \"0\")\n\n    --offset-format|-o <fmt1[,fmt2]>    One or two of: dec, hex, humiec, humsi, oct, per, no, ''.\n                                        First one is displayed on the left side and second one on right side after formatters. (default: \"hex\")\n\n    --print-relative-offset|-r          Print relative offset(s) starting from 0 (file only) (default: false)\n\n    --seek|-s <[prefix]offset[unit]>    Start reading from certain offset. See NOTES. (default: \"0\")\n\n    --splitter|-S <size>                Insert visual splitter every N bytes. Zero (0) disables. (default: 8)\n\n    --version                           Show version information (default: false)\n\n    --width|-w <[prefix]width>          Width. See NOTES. (default: \"16\")\n\n\nNOTES:\n    - You can use prefixes for seek, limit and width. 0x = hex, 0b = binary, 0o = octal\n    - Use '--seek \\-1234' for seeking from end of file\n    - Limit and seek parameters supports units (KB, KiB, MB, MiB, GB, GiB, TB, TiB)\n    - --print-relative-offset can be used when seeking to certain offset to also print extra offset position starting from zero\n    - Offset formatters:\n      - Disable formatter output with 'no' or ''\n      - 'humiec' (IEC: 1024 B) and 'humsi' (SI: 1000 B) displays offset in human form (n KiB/KB)\n    - Formatters:\n      - 'blk' can be used to print simple color blocks which helps to visualize where data vs. human readable strings are\n\nEXAMPLES:\n    heksa -f hex,asc,bit foo.dat\n    heksa -o hex,per -f hex,asc foo.dat\n    heksa -o hex -f hex,asc,bit foo.dat\n    heksa -o no -f bit foo.dat\n    heksa -l 0x1024 foo.dat\n    heksa -s 0b1010 foo.dat\n    heksa -s 4321KiB foo.dat\n    heksa -w 8 foo.dat\n    echo \"test\" | heksa\n```\n\n## Requirements\n\n* Terminal with ANSI color support\n  * [KDE](https://kde.org/)'s [Konsole](https://konsole.kde.org/) is currently used for development\n* Operating system\n  * [GNU/Linux](https://www.gnu.org/distros/distros.html)\n    * x64 arm arm64 ppc64 ppc64le\n  * [Microsoft Windows](https://www.microsoft.com/en-us/windows)\n    * x64\n  * [Darwin](https://www.apple.com/macos/) (Apple Mac)\n    * x64\n  * [FreeBSD](https://www.freebsd.org/)\n    * x64 arm\n  * [NetBSD](https://www.netbsd.org/)\n    * x64 arm\n  * [OpenBSD](https://www.openbsd.org/)\n    * x64 arm arm64\n  * Other OSes supported by [Go](https://golang.org)\n    * For full list, see: https://go.dev/doc/install/source#environment\n\n## Get source\n\n    git clone https://github.com/raspi/heksa\n\n## Contributing and helping with the project\n\nSee [CONTRIBUTING.md](CONTRIBUTING.md) and [current issues](https://github.com/raspi/heksa/issues) that might need help.\n\n## Developing\n\n1. Make changes\n1. `make build` or just `go build .`\n\n## Releasing new version:\n\nRequirements:\n\n* `upx` for compressing executables\n\n1. Create new version tag\n1. `make release`\n\nIf there's a lot of visual changes you can take new screenshots with `screenshot.sh` script in [_assets](_assets) directory\n\n## Is it any good?\n\nYes."
}
