{
  "name": "jscpd",
  "full_name": "jscpd",
  "tap": "homebrew/core",
  "oldname": null,
  "oldnames": [],
  "aliases": [],
  "versioned_formulae": [],
  "desc": "Copy/paste detector for programming source code",
  "license": "MIT",
  "homepage": "https://github.com/kucherenko/jscpd",
  "versions": {
    "stable": "3.5.9",
    "head": null,
    "bottle": true
  },
  "urls": {
    "stable": {
      "url": "https://registry.npmjs.org/jscpd/-/jscpd-3.5.9.tgz",
      "tag": null,
      "revision": null,
      "checksum": "e211ce3f662cb60b2f292bf35bcbd1509d91ccadeac496d0fdca11f5fedc8a4a"
    }
  },
  "revision": 0,
  "version_scheme": 0,
  "bottle": {
    "stable": {
      "rebuild": 0,
      "root_url": "https://ghcr.io/v2/homebrew/core",
      "files": {
        "arm64_ventura": {
          "cellar": ":any_skip_relocation",
          "url": "https://ghcr.io/v2/homebrew/core/jscpd/blobs/sha256:9ffdb869994ed687e2ba055b34db404126b4c2f2eb897e21144a06fe17f063ad",
          "sha256": "9ffdb869994ed687e2ba055b34db404126b4c2f2eb897e21144a06fe17f063ad"
        },
        "arm64_monterey": {
          "cellar": ":any_skip_relocation",
          "url": "https://ghcr.io/v2/homebrew/core/jscpd/blobs/sha256:9ffdb869994ed687e2ba055b34db404126b4c2f2eb897e21144a06fe17f063ad",
          "sha256": "9ffdb869994ed687e2ba055b34db404126b4c2f2eb897e21144a06fe17f063ad"
        },
        "arm64_big_sur": {
          "cellar": ":any_skip_relocation",
          "url": "https://ghcr.io/v2/homebrew/core/jscpd/blobs/sha256:9ffdb869994ed687e2ba055b34db404126b4c2f2eb897e21144a06fe17f063ad",
          "sha256": "9ffdb869994ed687e2ba055b34db404126b4c2f2eb897e21144a06fe17f063ad"
        },
        "ventura": {
          "cellar": ":any_skip_relocation",
          "url": "https://ghcr.io/v2/homebrew/core/jscpd/blobs/sha256:c8769fe5ac5ac82db915f871d0970dc003d62bde9edd9921db5632f9dc9f8ffa",
          "sha256": "c8769fe5ac5ac82db915f871d0970dc003d62bde9edd9921db5632f9dc9f8ffa"
        },
        "monterey": {
          "cellar": ":any_skip_relocation",
          "url": "https://ghcr.io/v2/homebrew/core/jscpd/blobs/sha256:c8769fe5ac5ac82db915f871d0970dc003d62bde9edd9921db5632f9dc9f8ffa",
          "sha256": "c8769fe5ac5ac82db915f871d0970dc003d62bde9edd9921db5632f9dc9f8ffa"
        },
        "big_sur": {
          "cellar": ":any_skip_relocation",
          "url": "https://ghcr.io/v2/homebrew/core/jscpd/blobs/sha256:c8769fe5ac5ac82db915f871d0970dc003d62bde9edd9921db5632f9dc9f8ffa",
          "sha256": "c8769fe5ac5ac82db915f871d0970dc003d62bde9edd9921db5632f9dc9f8ffa"
        },
        "x86_64_linux": {
          "cellar": ":any_skip_relocation",
          "url": "https://ghcr.io/v2/homebrew/core/jscpd/blobs/sha256:9ffdb869994ed687e2ba055b34db404126b4c2f2eb897e21144a06fe17f063ad",
          "sha256": "9ffdb869994ed687e2ba055b34db404126b4c2f2eb897e21144a06fe17f063ad"
        }
      }
    }
  },
  "keg_only": false,
  "keg_only_reason": null,
  "options": [],
  "build_dependencies": [],
  "dependencies": [
    "node"
  ],
  "test_dependencies": [],
  "recommended_dependencies": [],
  "optional_dependencies": [],
  "uses_from_macos": [],
  "uses_from_macos_bounds": [],
  "requirements": [],
  "conflicts_with": [],
  "conflicts_with_reasons": [],
  "link_overwrite": [],
  "caveats": null,
  "installed": [],
  "linked_keg": null,
  "pinned": false,
  "outdated": false,
  "deprecated": false,
  "deprecation_date": null,
  "deprecation_reason": null,
  "disabled": false,
  "disable_date": null,
  "disable_reason": null,
  "post_install_defined": false,
  "service": null,
  "tap_git_head": "4eeae4ea50839e967536ba646d5e0ed6fbcbad7f",
  "ruby_source_path": "Formula/jscpd.rb",
  "ruby_source_checksum": {
    "sha256": "1826b90429cc95112a9d130386849b39a20e33287c02db210c2e3378bf3718ab"
  },
  "date_added": "2022-12-08T15:51:06+00:00",
  "readme": "\n<p align=\"center\">\n  <img src=\"https://raw.githubusercontent.com/kucherenko/jscpd/master/assets/logo.svg?sanitize=true\">\n</p>\n\n## jscpd\n\n![stand with Ukraine](https://badgen.net/badge/support/UKRAINE/?color=0057B8&labelColor=FFD700)\n\n[![npm](https://img.shields.io/npm/v/jscpd.svg?style=flat-square)](https://www.npmjs.com/package/jscpd)\n![jscpd](https://raw.githubusercontent.com/kucherenko/jscpd/master/assets/jscpd-badge.svg?sanitize=true)\n[![license](https://img.shields.io/github/license/kucherenko/jscpd.svg?style=flat-square)](https://github.com/kucherenko/jscpd/blob/master/LICENSE)\n[![npm](https://img.shields.io/npm/dw/jscpd.svg?style=flat-square)](https://www.npmjs.com/package/jscpd)\n\n\n[![jscpd CI](https://github.com/kucherenko/jscpd/actions/workflows/nodejs.yml/badge.svg)](https://github.com/kucherenko/jscpd/actions/workflows/nodejs.yml)\n[![codecov](https://codecov.io/gh/kucherenko/jscpd/branch/master/graph/badge.svg)](https://codecov.io/gh/kucherenko/jscpd)\n[![FOSSA Status](https://app.fossa.io/api/projects/git%2Bgithub.com%2Fkucherenko%2Fjscpd.svg?type=shield)](https://app.fossa.io/projects/git%2Bgithub.com%2Fkucherenko%2Fjscpd?ref=badge_shield)\n[![Backers on Open Collective](https://opencollective.com/jscpd/backers/badge.svg)](#backers)\n[![Sponsors on Open Collective](https://opencollective.com/jscpd/sponsors/badge.svg)](#sponsors)\n\n[![NPM](https://nodei.co/npm/jscpd.svg)](https://nodei.co/npm/jscpd/)\n\n> Copy/paste detector for programming source code, supports 150+ formats.\n\nCopy/paste is a common technical debt on a lot of projects. The jscpd gives the ability to find duplicated blocks implemented on more than 150 programming languages and digital formats of documents.\nThe jscpd tool implements [Rabin-Karp](https://en.wikipedia.org/wiki/Rabin%E2%80%93Karp_algorithm) algorithm for searching duplications.\n\n## Packages of jscpd\n\n| name                 | version  |  description  |\n|----------------------|----------|---------------|\n| [jscpd](packages/jscpd) | [![npm](https://img.shields.io/npm/v/jscpd.svg?style=flat-square)](https://www.npmjs.com/package/jscpd) | main package for jscpd (cli and API for detections included) |\n| [@jscpd/core](packages/core) | [![npm](https://img.shields.io/npm/v/@jscpd/core.svg?style=flat-square)](https://www.npmjs.com/package/@jscpd/core) |core detection algorithm, can be used for detect duplication in different environments, one dependency to eventemitter3 |\n| [@jscpd/finder](packages/finder) | [![npm](https://img.shields.io/npm/v/@jscpd/finder.svg?style=flat-square)](https://www.npmjs.com/package/@jscpd/finder) | detector of duplication in files  |\n| [@jscpd/tokenizer](packages/tokenizer) | [![npm](https://img.shields.io/npm/v/@jscpd/tokenizer.svg?style=flat-square)](https://www.npmjs.com/package/@jscpd/tokenizer) | tool for tokenize programming source code |\n| [@jscpd/leveldb-store](packages/leveldb-store) | [![npm](https://img.shields.io/npm/v/@jscpd/leveldb-store.svg?style=flat-square)](https://www.npmjs.com/package/@jscpd/leveldb-store) | LevelDB store, used for big repositories, slower than default store |\n| [@jscpd/html-reporter](packages/html-reporter) | [![npm](https://img.shields.io/npm/v/@jscpd/html-reporter.svg?style=flat-square)](https://www.npmjs.com/package/@jscpd/html-reporter) | Html reporter for jscpd |\n| [@jscpd/badge-reporter](packages/badge-reporter) | [![npm](https://img.shields.io/npm/v/@jscpd/badge-reporter.svg?style=flat-square)](https://www.npmjs.com/package/@jscpd/badge-reporter) | Badge reporter for jscpd |\n\n## Installation\n```bash\n$ npm install -g jscpd\n```\n## Usage\n```bash\n$ npx jscpd /path/to/source\n```\nor\n\n```bash\n$ jscpd /path/to/code\n```\nor\n\n```bash\n$ jscpd --pattern \"src/**/*.js\"\n```\nMore information about cli [here](packages/jscpd).\n\n## Programming API\n\nFor integration copy/paste detection to your application you can use programming API:\n\n`jscpd` Promise API\n```typescript\nimport {IClone} from '@jscpd/core';\nimport {jscpd} from 'jscpd';\n\nconst clones: Promise<IClone[]> = jscpd(process.argv);\n```\n\n`jscpd` async/await API\n```typescript\nimport {IClone} from '@jscpd/core';\nimport {jscpd} from 'jscpd';\n(async () => {\n  const clones: IClone[] = await jscpd(['', '', __dirname + '/../fixtures', '-m', 'weak', '--silent']);\n  console.log(clones);\n})();\n\n```\n\n`detectClones` API\n```typescript\nimport {detectClones} from \"jscpd\";\n\n(async () => {\n  const clones = await detectClones({\n    path: [\n      __dirname + '/../fixtures'\n    ],\n    silent: true\n  });\n  console.log(clones);\n})()\n```\n\n`detectClones` with persist store\n```typescript\nimport {detectClones} from \"jscpd\";\nimport {IMapFrame, MemoryStore} from \"@jscpd/core\";\n\n(async () => {\n  const store = new MemoryStore<IMapFrame>();\n\n  await detectClones({\n    path: [\n      __dirname + '/../fixtures'\n    ],\n  }, store);\n\n  await detectClones({\n    path: [\n      __dirname + '/../fixtures'\n    ],\n    silent: true\n  }, store);\n})()\n```\n\nIn case of deep customisation of detection process you can build your own tool with `@jscpd/core`, `@jscpd/finder` and `@jscpd/tokenizer`.\n\n## Start contribution\n\n - Fork the repo [kucherenko/jscpd](https://github.com/kucherenko/jscpd/)\n - Clone forked version (`git clone https://github.com/{your-id}/jscpd`)\n - Install dependencies (`yarn install`)\n - Add your changes\n - Add tests and check it with `yarn test`\n - Create PR\n\n## Who uses jscpd\n - [GitHub Super Linter](https://github.com/github/super-linter) is combination of multiple linters to install as a GitHub Action\n - [Code-Inspector](https://www.code-inspector.com/) is a code analysis and technical debt management service.\n - [Mega-Linter](https://nvuillam.github.io/mega-linter/) is a 100% open-source linters aggregator for CI (GitHub Action & other CI tools) or to run locally\n - [Codacy](http://docs.codacy.com/getting-started/supported-languages-and-tools/) automatically analyzes your source code and identifies issues as you go, helping you develop software more efficiently with fewer issues down the line.\n - [Natural](https://github.com/NaturalNode/natural) is a general natural language facility for nodejs. It offers a broad range of functionalities for natural language processing.\n\n\n## Backers\n\nThank you to all our backers! 🙏 [[Become a backer](https://opencollective.com/jscpd#backer)]\n\n<a href=\"https://opencollective.com/jscpd#backers\" target=\"_blank\"><img src=\"https://opencollective.com/jscpd/backers.svg?width=890\"></a>\n## Sponsors\n\nSupport this project by becoming a sponsor. Your logo will show up here with a link to your website. [[Become a sponsor](https://opencollective.com/jscpd#sponsor)]\n\n<a href=\"https://opencollective.com/jscpd/sponsor/0/website\" target=\"_blank\"><img src=\"https://opencollective.com/jscpd/sponsor/0/avatar.svg\"></a>\n<a href=\"https://opencollective.com/jscpd/sponsor/1/website\" target=\"_blank\"><img src=\"https://opencollective.com/jscpd/sponsor/1/avatar.svg\"></a>\n<a href=\"https://opencollective.com/jscpd/sponsor/2/website\" target=\"_blank\"><img src=\"https://opencollective.com/jscpd/sponsor/2/avatar.svg\"></a>\n<a href=\"https://opencollective.com/jscpd/sponsor/3/website\" target=\"_blank\"><img src=\"https://opencollective.com/jscpd/sponsor/3/avatar.svg\"></a>\n<a href=\"https://opencollective.com/jscpd/sponsor/4/website\" target=\"_blank\"><img src=\"https://opencollective.com/jscpd/sponsor/4/avatar.svg\"></a>\n<a href=\"https://opencollective.com/jscpd/sponsor/5/website\" target=\"_blank\"><img src=\"https://opencollective.com/jscpd/sponsor/5/avatar.svg\"></a>\n<a href=\"https://opencollective.com/jscpd/sponsor/6/website\" target=\"_blank\"><img src=\"https://opencollective.com/jscpd/sponsor/6/avatar.svg\"></a>\n<a href=\"https://opencollective.com/jscpd/sponsor/7/website\" target=\"_blank\"><img src=\"https://opencollective.com/jscpd/sponsor/7/avatar.svg\"></a>\n<a href=\"https://opencollective.com/jscpd/sponsor/8/website\" target=\"_blank\"><img src=\"https://opencollective.com/jscpd/sponsor/8/avatar.svg\"></a>\n<a href=\"https://opencollective.com/jscpd/sponsor/9/website\" target=\"_blank\"><img src=\"https://opencollective.com/jscpd/sponsor/9/avatar.svg\"></a>\n\n![ga tracker](https://www.google-analytics.com/collect?v=1&a=257770996&t=pageview&dl=https%3A%2F%2Fgithub.com%2Fkucherenko%2Fjscpd&ul=en-us&de=UTF-8&cid=978224512.1377738459&tid=UA-730549-17&z=887657232 \"ga tracker\")\n\n## License\n\n[MIT](LICENSE) © Andrey Kucherenko"
}
