{
  "name": "lsof",
  "full_name": "lsof",
  "tap": "homebrew/core",
  "oldname": null,
  "oldnames": [],
  "aliases": [],
  "versioned_formulae": [],
  "desc": "Utility to list open files",
  "license": "Zlib",
  "homepage": "https://github.com/lsof-org/lsof",
  "versions": {
    "stable": "4.98.0",
    "head": null,
    "bottle": true
  },
  "urls": {
    "stable": {
      "url": "https://github.com/lsof-org/lsof/archive/refs/tags/4.98.0.tar.gz",
      "tag": null,
      "revision": null,
      "checksum": "80308a614508814ac70eb2ae1ed2c4344dcf6076fa60afc7734d6b1a79e62b16"
    }
  },
  "revision": 0,
  "version_scheme": 0,
  "bottle": {
    "stable": {
      "rebuild": 0,
      "root_url": "https://ghcr.io/v2/homebrew/core",
      "files": {
        "arm64_ventura": {
          "cellar": ":any_skip_relocation",
          "url": "https://ghcr.io/v2/homebrew/core/lsof/blobs/sha256:fa116c39661d0d7b685897977dd5d90c384557baeb7dbeef0ab261cc8bd36e74",
          "sha256": "fa116c39661d0d7b685897977dd5d90c384557baeb7dbeef0ab261cc8bd36e74"
        },
        "arm64_monterey": {
          "cellar": ":any_skip_relocation",
          "url": "https://ghcr.io/v2/homebrew/core/lsof/blobs/sha256:d5b2be9ee891a5cb62e3e2d68c6513d9a7b27fa414acae729242a1abdbe93135",
          "sha256": "d5b2be9ee891a5cb62e3e2d68c6513d9a7b27fa414acae729242a1abdbe93135"
        },
        "arm64_big_sur": {
          "cellar": ":any_skip_relocation",
          "url": "https://ghcr.io/v2/homebrew/core/lsof/blobs/sha256:90d939a92133f1221f24d45c5406412959aa38aeac6c3a884ba3dc7b9fbf6f84",
          "sha256": "90d939a92133f1221f24d45c5406412959aa38aeac6c3a884ba3dc7b9fbf6f84"
        },
        "ventura": {
          "cellar": ":any_skip_relocation",
          "url": "https://ghcr.io/v2/homebrew/core/lsof/blobs/sha256:0019c79578d74d752cf0589ff83c1b8b21a073327deb58b310ba59e9e46c4b09",
          "sha256": "0019c79578d74d752cf0589ff83c1b8b21a073327deb58b310ba59e9e46c4b09"
        },
        "monterey": {
          "cellar": ":any_skip_relocation",
          "url": "https://ghcr.io/v2/homebrew/core/lsof/blobs/sha256:c33f6a2ff078b538a77c1fa0475b1d409d7196dadfffab16b90d38a13d4ed38f",
          "sha256": "c33f6a2ff078b538a77c1fa0475b1d409d7196dadfffab16b90d38a13d4ed38f"
        },
        "big_sur": {
          "cellar": ":any_skip_relocation",
          "url": "https://ghcr.io/v2/homebrew/core/lsof/blobs/sha256:badaa07907718d5b13096cbfd3654afd65f36dc96ba0f7b382aa8ddd448a689d",
          "sha256": "badaa07907718d5b13096cbfd3654afd65f36dc96ba0f7b382aa8ddd448a689d"
        },
        "x86_64_linux": {
          "cellar": ":any_skip_relocation",
          "url": "https://ghcr.io/v2/homebrew/core/lsof/blobs/sha256:bb3f15624b78349297ca7a081f14b93a26a7f08d5cb78eda0c268ffbede36f4f",
          "sha256": "bb3f15624b78349297ca7a081f14b93a26a7f08d5cb78eda0c268ffbede36f4f"
        }
      }
    }
  },
  "keg_only": false,
  "keg_only_reason": {
    "reason": ":provided_by_macos",
    "explanation": ""
  },
  "options": [],
  "build_dependencies": [],
  "dependencies": [
    "libtirpc"
  ],
  "test_dependencies": [],
  "recommended_dependencies": [],
  "optional_dependencies": [],
  "uses_from_macos": [],
  "uses_from_macos_bounds": [],
  "requirements": [],
  "conflicts_with": [],
  "conflicts_with_reasons": [],
  "link_overwrite": [],
  "caveats": null,
  "installed": [],
  "linked_keg": null,
  "pinned": false,
  "outdated": false,
  "deprecated": false,
  "deprecation_date": null,
  "deprecation_reason": null,
  "disabled": false,
  "disable_date": null,
  "disable_reason": null,
  "post_install_defined": false,
  "service": null,
  "tap_git_head": "4eeae4ea50839e967536ba646d5e0ed6fbcbad7f",
  "ruby_source_path": "Formula/lsof.rb",
  "ruby_source_checksum": {
    "sha256": "02191f1791067ddc6531010544dd49cfb6d1bc8e4ee1cc7f7f7556dadc191749"
  },
  "date_added": "2010-01-16T10:36:32-08:00",
  "readme": "[![Circle CI](https://circleci.com/gh/lsof-org/lsof.svg?style=svg)](https://circleci.com/gh/lsof-org/lsof)\n[![Cirrus CI](https://img.shields.io/cirrus/github/lsof-org/lsof)](https://cirrus-ci.com/github/lsof-org/lsof)\n[![builds.sr.ht status](https://builds.sr.ht/~jiegec/lsof.svg)](https://builds.sr.ht/~jiegec/lsof?)\n[![Read the Docs](https://readthedocs.org/projects/lsof/badge/?version=latest)](https://lsof.readthedocs.io/en/latest/)\n\n# lsof\n\n[lsof](https://en.wikipedia.org/wiki/Lsof) is a command listing open files.\n\n## How it works:\n\n```\n$ cat > /tmp/LOG &\ncat > /tmp/LOG &\n[1] 18083\n$ lsof -p 18083\nlsof -p 18083\nCOMMAND   PID   USER   FD   TYPE DEVICE  SIZE/OFF     NODE NAME\ncat     18083 yamato  cwd    DIR   0,44      1580 43460784 /tmp/lsof\ncat     18083 yamato  rtd    DIR  253,2      4096        2 /\ncat     18083 yamato  txt    REG  253,2     47432   678364 /usr/bin/cat\ncat     18083 yamato  mem    REG  253,2 111950656   681778 /usr/lib/locale/locale-archive\ncat     18083 yamato  mem    REG  253,2   2119256   679775 /usr/lib64/libc-2.27.so\ncat     18083 yamato  mem    REG  253,2    187632   655943 /usr/lib64/ld-2.27.so\ncat     18083 yamato  mem    REG  253,2     26370   662532 /usr/lib64/gconv/gconv-modules.cache\ncat     18083 yamato  mem    REG  253,2      3316  1578981 /usr/lib/locale/en_US.utf8/LC_TIME\ncat     18083 yamato    0u   CHR  136,3       0t0        6 /dev/pts/3\ncat     18083 yamato    1w   REG   0,44         0 54550934 /tmp/LOG\ncat     18083 yamato    2u   CHR  136,3       0t0        6 /dev/pts/3\n```\n\nRead the documentation at [lsof.readthedocs.io](https://lsof.readthedocs.io/)\n\n# lsof-org at GitHub\n\nThe lsof-org team at GitHub takes over the maintainership of lsof originally\ndeveloped and maintained by Vic Abell. This repository is for maintaining the\nfinal source tree of lsof inherited from Vic. \"legacy\" branch keeps the original\nsource tree. We will not introduce any changes to the \"legacy\" branch. This\nbranch is just for reference.\n\n\"master\" branch is used for maintenance. Bug fixes and enhancements go to\n\"master\" branch.\n\nlsof had supported many OSes. A term \"dialect\" represents code for supporting\nOSes. Because of limited resources, we will maintain the part of them. The\ncurrent status of maintenance is as follows:\n\n<dl>\n<dt>FreeBSD</dt>\n<dd>fully maintained and tested on Cirrus CI</dd>\n<dt>Linux</dt>\n<dd>fully maintained, and tested on Circle CI</dd>\n<dt>Darwin</dt>\n<dd>fully maintained, and tested on Circle CI</dd>\n<dt>NetBSD</dt>\n<dd>fully maintained, and tested on SourceHut CI</dd>\n<dt>OpenBSD</dt>\n<dd>fully maintained, and tested on SourceHut CI</dd>\n<dt>Solaris/OpenIndiana</dt>\n<dd>fully maintained</dd>\n</dl>\n\nIf you are interested in maintaining a dialect, let us know via the issue\ntracker of GitHub (https://github.com/lsof-org/lsof/issues). If we cannot find a\nvolunteer for a dialect, we will remove the dialect.\n\nMany texts in the source tree still refers purdue.edu as the home of lsof\ndevelopment. It should be https://github.com/lsof-org/lsof, the new home. The\nupdating is in progress.\n\nWe ran another repository, lsof-org/\"lsof-linux\" derived from lsof-4.91 that was\nalso released by Vic. The repository is no more used; all the changes made in\nthe repository are now in lsof-org/\"lsof\" repository.\n\nThe lsof-org team at GitHub"
}
