{
  "name": "sub2srt",
  "full_name": "sub2srt",
  "tap": "homebrew/core",
  "oldname": null,
  "oldnames": [],
  "aliases": [],
  "versioned_formulae": [],
  "desc": "Convert subtitles from .sub to subviewer .srt format",
  "license": "GPL-2.0-or-later",
  "homepage": "https://github.com/robelix/sub2srt",
  "versions": {
    "stable": "0.5.5",
    "head": "HEAD",
    "bottle": true
  },
  "urls": {
    "stable": {
      "url": "https://github.com/robelix/sub2srt/archive/0.5.5.tar.gz",
      "tag": null,
      "revision": null,
      "checksum": "169d94d1d0e946a5d57573b7b7b5883875996f802362341fe1a1a0220229b905"
    },
    "head": {
      "url": "https://github.com/robelix/sub2srt.git",
      "branch": "master"
    }
  },
  "revision": 0,
  "version_scheme": 0,
  "bottle": {
    "stable": {
      "rebuild": 1,
      "root_url": "https://ghcr.io/v2/homebrew/core",
      "files": {
        "all": {
          "cellar": ":any_skip_relocation",
          "url": "https://ghcr.io/v2/homebrew/core/sub2srt/blobs/sha256:b13ea475d840e7fbe89a3c035e7552debd0e355abc8bfce97d476b8d912e2137",
          "sha256": "b13ea475d840e7fbe89a3c035e7552debd0e355abc8bfce97d476b8d912e2137"
        }
      }
    }
  },
  "keg_only": false,
  "keg_only_reason": null,
  "options": [],
  "build_dependencies": [],
  "dependencies": [],
  "test_dependencies": [],
  "recommended_dependencies": [],
  "optional_dependencies": [],
  "uses_from_macos": [
    "perl"
  ],
  "uses_from_macos_bounds": [
    {}
  ],
  "requirements": [],
  "conflicts_with": [],
  "conflicts_with_reasons": [],
  "link_overwrite": [],
  "caveats": null,
  "installed": [],
  "linked_keg": null,
  "pinned": false,
  "outdated": false,
  "deprecated": false,
  "deprecation_date": null,
  "deprecation_reason": null,
  "disabled": false,
  "disable_date": null,
  "disable_reason": null,
  "post_install_defined": false,
  "service": null,
  "tap_git_head": "4eeae4ea50839e967536ba646d5e0ed6fbcbad7f",
  "ruby_source_path": "Formula/sub2srt.rb",
  "ruby_source_checksum": {
    "sha256": "6991d0a053114d3993b988c6090b20d12486b1781f0c541ac40db8001527a6d6"
  },
  "date_added": "2010-10-30T18:35:22-07:00"
}
